{
  "extracted_at": "2025-03-02T19:31:48.929725+00:00",
  "status": "processed",
  "context_type": "files",
  "context_name": "Knesset Bylaws (תקנון הכנסת) and related laws",
  "source_content": "**חוק-יסוד: הכנסת: **\n\n[מקור: סעיף 17. ](https://he.wikisource.org/wiki/%D7%97%D7%95%D7%A7-%D7%99%D7%A1%D7%95%D7%93:_%D7%94%D7%9B%D7%A0%D7%A1%D7%AA#%D7%A1%D7%A2%D7%99%D7%A3_17)\nחסינות חברי הכנסת\nלחברי הכנסת תהיה חסינות; פרטים ייקבעו בחוק.ראוחוק חסינות חברי הכנסת, זכויותיהם וחובותיהם, תשי״א–1951.",
  "document_type": "חוק-יסוד: הכנסת",
  "extracted_data": {
    "DocumentMetadata": {
      "DocumentTitle": "חוק-יסוד: הכנסת",
      "PublicationDate": "",
      "OfficialSource": "סעיף 17",
      "ReferenceLinks": [
        "https://he.wikisource.org/wiki/%D7%97%D7%95%D7%A7-%D7%99%D7%A1%D7%95%D7%93:_%D7%94%D7%9B%D7%A0%D7%A1%D7%AA#%D7%A1%D7%A2%D7%99%D7%A3_17"
      ],
      "Language": "עברית",
      "Version": "",
      "ClauseRepresentation": "main clause",
      "OfficialRoles": [],
      "OfficialOrganizations": [],
      "Placenames": [],
      "Description": "חוק המפרט את חסינות חברי הכנסת."
    },
    "LegalReferences": [
      {
        "ReferenceTitle": "חוק חסינות חברי הכנסת",
        "ReferenceText": "זכויותיהם וחובותיהם, תשי״א–1951",
        "ReferenceQuote": "חוק חסינות חברי הכנסת, זכויותיהם וחובותיהם, תשי״א–1951."
      }
    ],
    "Amendments": [],
    "AdditionalKeywords": [
      "חסינות",
      "חברי הכנסת",
      "זכויות",
      "חובות"
    ],
    "Topics": []
  },
  "title": "חוק-יסוד: הכנסת",
  "source_file": "חוק-יסוד: הכנסת_17.md"
}